dbeasy/__init__.py
dbeasy/connections.py
dbeasy-0.7.dist-info/LICENSE
dbeasy-0.7.dist-info/METADATA
dbeasy-0.7.dist-info/WHEEL
dbeasy-0.7.dist-info/top_level.txt
dbeasy-0.7.dist-info/RECORD
